LICENSE
README.md
setup.cfg
setup.py
USJ_diptools.egg-info/PKG-INFO
USJ_diptools.egg-info/SOURCES.txt
USJ_diptools.egg-info/dependency_links.txt
USJ_diptools.egg-info/not-zip-safe
USJ_diptools.egg-info/requires.txt
USJ_diptools.egg-info/top_level.txt
diptools/__init__.py
diptools/bitlevel.py
diptools/filters.py
diptools/freqfilters.py
diptools/graph.py
diptools/pointprocessing.py
diptools/region.py
diptools/video.py
usj_diptools.egg-info/PKG-INFO
usj_diptools.egg-info/SOURCES.txt
usj_diptools.egg-info/dependency_links.txt
usj_diptools.egg-info/not-zip-safe
usj_diptools.egg-info/requires.txt
usj_diptools.egg-info/top_level.txt