Metadata-Version: 2.2
Name: usj_diptools
Version: 2025.3.14
Summary: A Python package to provide easy to use tools to learn and teach digital (biomedical) image processing with Python.
Home-page: https://github.com/aalcaineo/diptools
Author: Alejandro Alcaine, PhD
Author-email: lalcaine@usj.es
License: GNU General Public License v2.0
Keywords: Digital Signal Processing
Classifier: Development Status :: 3 - Alpha
Classifier: Intended Audience :: Developers
Classifier: Topic :: Software Development :: Build Tools
Classifier: Programming Language :: Python :: 3
Requires-Python: >=3.10
License-File: LICENSE
Requires-Dist: matplotlib>=3.7.0
Requires-Dist: numpy>=1.23.5
Requires-Dist: opencv-python>=4.9.0
Provides-Extra: dev
Requires-Dist: twine>=4.0.2; extra == "dev"
Dynamic: author
Dynamic: author-email
Dynamic: classifier
Dynamic: description
Dynamic: description-content-type
Dynamic: home-page
Dynamic: keywords
Dynamic: license
Dynamic: provides-extra
Dynamic: requires-dist
Dynamic: requires-python
Dynamic: summary
